Metadata-Version: 1.0
Name: distribute-bino-gauss
Version: 0.1
Summary: distributions for gaussian and binomial
Home-page: UNKNOWN
Author: hqv
Author-email: UNKNOWN
License: UNKNOWN
Platform: UNKNOWN
